bcpy/__init__.py
bcpy-0.0.1.dist-info/LICENSE
bcpy-0.0.1.dist-info/METADATA
bcpy-0.0.1.dist-info/WHEEL
bcpy-0.0.1.dist-info/top_level.txt
bcpy-0.0.1.dist-info/RECORD
