Metadata-Version: 2.1
Name: bcpy
Version: 0.0.1
Summary: Microsoft SQL Server bcp (Bulk Copy) wrapper
Home-page: https://github.com/titan550/bcpy
Author: John Shojaei
Author-email: titan550@gmail.com
License: UNKNOWN
Keywords: bcp mssql
Platform: UNKNOWN
Classifier: Topic :: Database
Classifier: Programming Language :: Python :: 3
Classifier: Programming Language :: SQL
Classifier: License :: OSI Approved :: MIT License
Classifier: Operating System :: OS Independent
